{
  "type": "FeatureCollection",
  "features": [
    { "type": "Feature",
      "properties": { "type": "elevator", "name": "Elevator TBT-1", "building": "TBT", "floor": 0 },
      "geometry": { "type": "Point", "coordinates": [-75.68967, 45.42371] }
    },
    { "type": "Feature",
      "properties": { "type": "ramp", "name": "Ramp MRT North", "building": "MRT", "floor": 0 },
      "geometry": { "type": "Point", "coordinates": [-75.68355, 45.42320] }
    },
    { "type": "Feature",
      "properties": { "type": "toilet", "name": "Accessible Washroom MRT-2F", "building": "MRT", "floor": 2 },
      "geometry": { "type": "Point", "coordinates": [-75.68350, 45.42312] }
    }
  ]
}
